{
  "attestation_schema": "robofox.main-validation-attestation.v1",
  "attested_at": "2026-07-14T16:44:27.920678+00:00",
  "deployment_triggered": false,
  "errors": 0,
  "external_evidence_complete": false,
  "failures": 0,
  "image_build": "passed",
  "migration": "head -> 0016 -> head passed",
  "production_approved": false,
  "ref": "refs/heads/main",
  "schema": "robofox.main-release-candidate.v1",
  "security": "pip-audit, Bandit and secret-pattern gates passed",
  "sha": "cb585b0ee59cbbb1b99f1f7904ff920bf3c20d31",
  "skipped": 0,
  "tests": 294,
  "validation_run_url": "https://github.com/febufenn-cyber/Acadensia/actions/runs/29350685662"
}
